pyaro/__init__.py
pyaro/mathutils.py
pyaro/pandas_helpers.py
pyaro/plugins.py
pyaro/csvreader/CSVTimeseriesReader.py
pyaro/csvreader/__init__.py
pyaro/timeseries/AutoFilterReaderEngine.py
pyaro/timeseries/Data.py
pyaro/timeseries/Engine.py
pyaro/timeseries/Filter.py
pyaro/timeseries/Reader.py
pyaro/timeseries/Station.py
pyaro/timeseries/Wrappers.py
pyaro/timeseries/__init__.py
pyaro-0.2.0.dist-info/licenses/LICENSE
pyaro-0.2.0.dist-info/METADATA
pyaro-0.2.0.dist-info/WHEEL
pyaro-0.2.0.dist-info/entry_points.txt
pyaro-0.2.0.dist-info/top_level.txt
pyaro-0.2.0.dist-info/RECORD
