Metadata-Version: 2.4
Name: pyaro
Version: 0.2.0
Summary: pyaro py-aerocom reader objects
Home-page: https://pyaro.readthedocs.io
Author: Heiko Klein, Daniel Heinesen
Author-email: Heiko.Klein@met.no
Classifier: Programming Language :: Python :: 3 :: Only
Classifier: Programming Language :: Python :: 3.10
Classifier: Programming Language :: Python :: 3.11
Classifier: Programming Language :: Python :: 3.12
Classifier: License :: OSI Approved :: GNU Lesser General Public License v3 (LGPLv3)
Classifier: Operating System :: OS Independent
Classifier: Development Status :: 4 - Beta
Classifier: Intended Audience :: Science/Research
Classifier: Intended Audience :: Education
Classifier: Topic :: Scientific/Engineering :: Atmospheric Science
License-File: LICENSE
Requires-Dist: numpy>=1.13
Requires-Dist: importlib-metadata>=3.6; python_version < "3.10"
Provides-Extra: optional
Requires-Dist: pandas; extra == "optional"
Requires-Dist: cf-units; extra == "optional"
Requires-Dist: xarray; extra == "optional"
Requires-Dist: netcdf4; extra == "optional"
Dynamic: license-file
